{
    "homeCamera": {
        "north": 36.10309,
        "east": 138.21846,
        "south": 35.93152,
        "west": 138.21601
    },
    "initialCamera": {
        "north": 35.99786756575103,
        "east": 138.18057511279886,
        "south": 35.98872791188594,
        "west": 138.16248310779358,
        "direction": {
            "x": 0.6984744646088341,
            "y": -0.6617056496661655,
            "z": 0.2725418417221117
        },
        "position": {
            "x": -3851258.9373411336,
            "y": 3446919.7199341212,
            "z": 3727721.354611991
        },
        "up": {
            "x": -0.21791222301017105,
            "y": 0.1660947782238842,
            "z": 0.9617311410729739
        }
    },
    "corsDomains": [
        "d300u3e35jef5x.cloudfront.net",
        "gic-plateau.s3.ap-northeast-1.amazonaws.com",
        "gibs.earthdata.nasa.gov"
    ],
    "baseMaps": {
        "items": [
            {
                "item": {
                    "type": "composite",
                    "id": "/basemap//航空写真",
                    "name": "航空写真",
                    "members": [
                        {
                            "type": "cesium-terrain",
                            "id": "/basemap//航空写真/terrain",
                            "name": "plateau-terrain",
                            "ionAccessToken": "eyJhbGciOiJIUzI1NiIsInR5cCI6IkpXVCJ9.eyJqdGkiOiI5N2UyMjcwOS00MDY1LTQxYjEtYjZjMy00YTU0ZTg5MmViYWQiLCJpZCI6ODAzMDYsImlhdCI6MTY0Mjc0ODI2MX0.dkwAL1CcljUV7NA7fDbhXXnmyZQU_c-G5zRx8PtEcxE",
                            "ionAssetId": 770371,
                            "attribution": "<a href='https://github.com/Project-PLATEAU/plateau-streaming-tutorial/blob/main/terrain/plateau-terrain-streaming.md'>PLATEAU-Terrain</a>"
                        },
                        {
                            "type": "open-street-map",
                            "opacity": 1,
                            "id": "/basemap//航空写真/imagery",
                            "name": "aerial-photo",
                            "url": "https://cyberjapandata.gsi.go.jp/xyz/seamlessphoto/",
                            "fileExtension": "jpg",
                            "attribution": "地理院タイル (<a href='https://www.gsi.go.jp/' target='_blank' rel='noopener noreferrer'>国土地理院</a>) / Shoreline data is derived from: United States. National Imagery and Mapping Agency. \"Vector Map Level 0 (VMAP0).\" Bethesda, MD: Denver, CO: The Agency; USGS Information Services, 1997."
                        }
                    ]
                },
                "image": "./images/aerophoto.png"
            },
            {
                "item": {
                    "type": "composite",
                    "id": "/basemap//全国最新写真 (シームレス)",
                    "name": "全国最新写真 (シームレス)",
                    "members": [
                        {
                            "type": "cesium-terrain",
                            "id": "/basemap//全国最新写真 (シームレス)/terrain",
                            "name": "tokyo-23ku-terrain",
                            "ionAccessToken": "eyJhbGciOiJIUzI1NiIsInR5cCI6IkpXVCJ9.eyJqdGkiOiI3NGI5ZDM0Mi1jZDIzLTRmMzEtOTkwYi0zZTk4Yzk3ODZlNzQiLCJpZCI6NDA2NDYsImlhdCI6MTYwODk4MzAwOH0.3rco62ErML11TMSEflsMqeUTCDbIH6o4n4l5sssuedE",
                            "ionAssetId": 286503,
                            "attribution": "地形データ：基盤地図情報数値標高モデルから作成（測量法に基づく国土地理院長承認（使用）R 3JHs 259）"
                        },
                        {
                            "type": "open-street-map",
                            "opacity": 1,
                            "id": "/basemap//航空写真/imagery",
                            "name": "航空写真",
                            "url": "https://gic-plateau.s3.ap-northeast-1.amazonaws.com/2020/ortho/tiles/",
                            "fileExtension": "png",
                            "attribution": "東京23区の地形と空中写真"
                        },
                        {
                            "type": "open-street-map",
                            "opacity": 1,
                            "id": "/basemap//全国最新写真 (シームレス)/imagery",
                            "name": "全国最新写真 (シームレス)",
                            "url": "https://cyberjapandata.gsi.go.jp/xyz/seamlessphoto/",
                            "fileExtension": "jpg",
                            "attribution": "地理院タイル (<a href='https://www.gsi.go.jp/' target='_blank' rel='noopener noreferrer'>国土地理院</a>) / Shoreline data is derived from: United States. National Imagery and Mapping Agency. \"Vector Map Level 0 (VMAP0).\" Bethesda, MD: Denver, CO: The Agency; USGS Information Services, 1997."
                        }
                    ]
                },
                "image": "./images/bgmap_tokyo.png"
            },
            {
                "item": {
                    "type": "composite",
                    "id": "/basemap//空中写真 (Bing)",
                    "name": "空中写真 (Bing)",
                    "members": [
                        {
                            "type": "cesium-terrain",
                            "id": "/basemap//全国最新写真 (シームレス)/terrain",
                            "name": "tokyo-23ku-terrain",
                            "ionAccessToken": "eyJhbGciOiJIUzI1NiIsInR5cCI6IkpXVCJ9.eyJqdGkiOiI3NGI5ZDM0Mi1jZDIzLTRmMzEtOTkwYi0zZTk4Yzk3ODZlNzQiLCJpZCI6NDA2NDYsImlhdCI6MTYwODk4MzAwOH0.3rco62ErML11TMSEflsMqeUTCDbIH6o4n4l5sssuedE",
                            "ionAssetId": 286503,
                            "attribution": "地形データ：基盤地図情報数値標高モデルから作成（測量法に基づく国土地理院長承認（使用）R 3JHs 259）"
                        },
                        {
                            "id": "/basemap//空中写真 (Bing)/imagery",
                            "name": "空中写真 (Bing)",
                            "type": "ion-imagery",
                            "ionAssetId": 3,
                            "opacity": 1
                        }
                    ]
                },
                "image": "./images/bgmap_bing.png"
            },
            {
                "item": {
                    "type": "composite",
                    "id": "/basemap//地理院地図 (淡色)",
                    "name": "地理院地図 (淡色)",
                    "members": [
                        {
                            "type": "cesium-terrain",
                            "id": "/basemap//全国最新写真 (シームレス)/terrain",
                            "name": "tokyo-23ku-terrain",
                            "ionAccessToken": "eyJhbGciOiJIUzI1NiIsInR5cCI6IkpXVCJ9.eyJqdGkiOiI3NGI5ZDM0Mi1jZDIzLTRmMzEtOTkwYi0zZTk4Yzk3ODZlNzQiLCJpZCI6NDA2NDYsImlhdCI6MTYwODk4MzAwOH0.3rco62ErML11TMSEflsMqeUTCDbIH6o4n4l5sssuedE",
                            "ionAssetId": 286503,
                            "attribution": "地形データ：基盤地図情報数値標高モデルから作成（測量法に基づく国土地理院長承認（使用）R 3JHs 259）"
                        },
                        {
                            "type": "open-street-map",
                            "opacity": 1,
                            "id": "/basemap//地理院地図 (淡色)/imagery",
                            "name": "地理院地図 (淡色)",
                            "url": "https://cyberjapandata.gsi.go.jp/xyz/pale/",
                            "fileExtension": "png",
                            "attribution": "地理院タイル (<a href='https://www.gsi.go.jp/' target='_blank' rel='noopener noreferrer'>国土地理院</a>) / Shoreline data is derived from: United States. National Imagery and Mapping Agency. \"Vector Map Level 0 (VMAP0).\" Bethesda, MD: Denver, CO: The Agency; USGS Information Services, 1997."
                        }
                    ]
                },
                "image": "./images/bgmap_gsi.png"
            },
            {
                "item": {
                    "type": "composite",
                    "id": "/basemap//Dark Matter",
                    "name": "Dark Matter",
                    "members": [
                        {
                            "type": "cesium-terrain",
                            "id": "/basemap//全国最新写真 (シームレス)/terrain",
                            "name": "tokyo-23ku-terrain",
                            "ionAccessToken": "eyJhbGciOiJIUzI1NiIsInR5cCI6IkpXVCJ9.eyJqdGkiOiI3NGI5ZDM0Mi1jZDIzLTRmMzEtOTkwYi0zZTk4Yzk3ODZlNzQiLCJpZCI6NDA2NDYsImlhdCI6MTYwODk4MzAwOH0.3rco62ErML11TMSEflsMqeUTCDbIH6o4n4l5sssuedE",
                            "ionAssetId": 286503,
                            "attribution": "地形データ：基盤地図情報数値標高モデルから作成（測量法に基づく国土地理院長承認（使用）R 3JHs 259）"
                        },
                        {
                            "type": "open-street-map",
                            "opacity": 1,
                            "id": "/basemap//basemap-darkmatter/imagery",
                            "name": "Dark Matter",
                            "url": "https://basemaps.cartocdn.com/dark_all/",
                            "fileExtension": "png",
                            "attribution": "© <a href'https://www.openstreetmap.org/copyright'>OpenStreetMap</a>, © <a href='https://carto.com/about-carto/'>CARTO</a>"
                        }
                    ]
                },
                "image": "./images/bgmap_darkmatter.png"
            }
        ],
        "enabledBaseMaps": [
            "/basemap//航空写真",
            "/basemap//全国最新写真 (シームレス)",
            "/basemap//空中写真 (Bing)",
            "/basemap//地理院地図 (淡色)",
            "/basemap//Dark Matter"
        ]
    },
    "catalog": [
        {
            "id": "//ランドマーク",
            "name": "ランドマーク",
            "type": "group",
            "isOpenInWorkbench": true,
            "members": [
                {
                    "id": "//ランドマーク/ランドマーク",
                    "name": "ランドマーク",
                    "type": "czml",
                    "hideSource": true,
                    "url": "/gis/landmark/landmark.czml",
                    "legends": [
                        {
                          "url": "./images/customicons/landmark.png",
                          "imageScaling": 1.0
                        }
                      ]
                }
            ]
        },
        {
            "id": "//3D都市モデル",
            "name": "3D都市モデル",
            "type": "group",
            "isOpenInWorkbench": true,
            "members": [
                {
                    "id": "//3D都市モデル/建物モデル（○○市）",
                    "name": "建物モデル（○○市）",
                    "type": "3d-tiles",
                    "hideSource": true,
                    "url": "/gis/3dtiles/building/texture/tileset.json",
                    "legends": [
                        {
                          "url": "./images/customicons/building_model.png",
                          "imageScaling": 1.0
                        }
                      ]
                }
            ]
        },
        {
            "id": "//災害情報",
            "name": "災害情報",
            "type": "group",
            "isOpenInWorkbench": false,
            "members": [
                {
                    "id": "//災害情報/浸水想定区域",
                    "name": "浸水想定区域",
                    "type": "wms",
                    "hideSource": true,
                    "url": "/geoserver/devps/wms",
                    "layers": "devps:flood_assumption"
                }
            ]
        },
        {
            "id": "//都市計画",
            "name": "都市計画",
            "type": "group",
            "isOpenInWorkbench": false,
            "members": [
                {
                    "id": "//都市計画/用途地域",
                    "name": "用途地域",
                    "type": "wms",
                    "hideSource": true,
                    "url": "/geoserver/devps/wms",
                    "layers": "devps:use_districts"
                },
                {
                    "id": "//都市計画/都市計画区域",
                    "name": "都市計画区域",
                    "type": "wms",
                    "hideSource": true,
                    "url": "/geoserver/devps/wms",
                    "layers": "devps:city_planning"
                },
                {
                    "id": "//都市計画/埋蔵文化財包蔵地域",
                    "name": "埋蔵文化財包蔵地域",
                    "type": "wms",
                    "hideSource": true,
                    "url": "/geoserver/devps/wms",
                    "layers": "devps:buried_cultural_property"
                }
            ]
        },
        {
            "id": "//その他",
            "name": "その他",
            "type": "group",
            "isOpenInWorkbench": false,
            "members": [
                {
                    "id": "//その他/農用地区域",
                    "name": "農用地区域",
                    "type": "wms",
                    "hideSource": true,
                    "url": "/geoserver/devps/wms",
                    "layers": "devps:agricultural_land"
                }
            ]
        }
    ],
    "workbench": ["//3D都市モデル/建物モデル（○○市）"]
}